{
	"info": {
		"_postman_id": "bedelia-api-collection",
		"name": "Bedelia API",
		"description": "REST API for Bedelia Course Management System\n\nThis collection provides read-only access to:\n- Carreras (Academic Programs)\n- Materias (Subjects/Courses)\n- Planes de Estudio (Study Plans)\n- Planes-Materias (Plan-Subject relationships)\n- Unidades Aprobables (Approvable Units)\n- Requisitos Nodos (Requirement Nodes)\n- Requisitos Items (Requirement Items)\n\nAll endpoints support filtering, searching, and ordering. Pagination is enabled with a default page size of 50 items.",
		"schema": "https://schema.getpostman.com/json/collection/v2.1.0/collection.json"
	},
	"item": [
		{
			"name": "Carreras",
			"item": [
				{
					"name": "List Carreras",
					"request": {
						"method": "GET",
						"header": [],
						"url": {
							"raw": "{{base_url}}/api/carreras/?search=&ordering=&page=",
							"host": [
								"{{base_url}}"
							],
							"path": [
								"api",
								"carreras",
								""
							],
							"query": [
								{
									"key": "search",
									"value": "",
									"description": "Search by carrera nombre",
									"disabled": true
								},
								{
									"key": "ordering",
									"value": "",
									"description": "Order by: nombre, fecha_creacion (prefix with - for descending)",
									"disabled": true
								},
								{
									"key": "page",
									"value": "",
									"description": "Page number for pagination",
									"disabled": true
								}
							]
						},
						"description": "List all carreras (academic programs).\n\n**Query Parameters:**\n- `search`: Search by carrera nombre\n- `ordering`: Order results by 'nombre' or 'fecha_creacion' (prefix with '-' for descending)\n- `page`: Page number for pagination (default page size: 50)\n\n**Example:**\n- `GET /api/carreras/?search=INGENIERIA&ordering=nombre`"
					},
					"response": [
						{
							"name": "Success Response",
							"originalRequest": {
								"method": "GET",
								"header": [],
								"url": {
									"raw": "{{base_url}}/api/carreras/",
									"host": [
										"{{base_url}}"
									],
									"path": [
										"api",
										"carreras",
										""
									]
								}
							},
							"status": "OK",
							"code": 200,
							"_postman_previewlanguage": "json",
							"header": [
								{
									"key": "Content-Type",
									"value": "application/json"
								}
							],
							"body": "{\n    \"count\": 10,\n    \"next\": null,\n    \"previous\": null,\n    \"results\": [\n        {\n            \"id\": \"123e4567-e89b-12d3-a456-426614174000\",\n            \"nombre\": \"INGENIERÍA CIVIL\",\n            \"fecha_creacion\": \"2024-01-01T00:00:00Z\",\n            \"fecha_modificacion\": \"2024-01-01T00:00:00Z\"\n        }\n    ]\n}"
						}
					]
				},
				{
					"name": "Get Carrera by ID",
					"request": {
						"method": "GET",
						"header": [],
						"url": {
							"raw": "{{base_url}}/api/carreras/:id/",
							"host": [
								"{{base_url}}"
							],
							"path": [
								"api",
								"carreras",
								":id",
								""
							],
							"variable": [
								{
									"key": "id",
									"value": "123e4567-e89b-12d3-a456-426614174000",
									"description": "UUID of the carrera"
								}
							]
						},
						"description": "Retrieve a specific carrera by its UUID.\n\n**Path Parameters:**\n- `id`: UUID of the carrera\n\n**Example:**\n- `GET /api/carreras/123e4567-e89b-12d3-a456-426614174000/`"
					},
					"response": [
						{
							"name": "Success Response",
							"originalRequest": {
								"method": "GET",
								"header": [],
								"url": {
									"raw": "{{base_url}}/api/carreras/123e4567-e89b-12d3-a456-426614174000/",
									"host": [
										"{{base_url}}"
									],
									"path": [
										"api",
										"carreras",
										"123e4567-e89b-12d3-a456-426614174000",
										""
									]
								}
							},
							"status": "OK",
							"code": 200,
							"_postman_previewlanguage": "json",
							"header": [
								{
									"key": "Content-Type",
									"value": "application/json"
								}
							],
							"body": "{\n    \"id\": \"123e4567-e89b-12d3-a456-426614174000\",\n    \"nombre\": \"INGENIERÍA CIVIL\",\n    \"fecha_creacion\": \"2024-01-01T00:00:00Z\",\n    \"fecha_modificacion\": \"2024-01-01T00:00:00Z\"\n}"
						}
					]
				}
			],
			"description": "Endpoints for managing carreras (academic programs)"
		},
		{
			"name": "Materias",
			"item": [
				{
					"name": "List Materias",
					"request": {
						"method": "GET",
						"header": [],
						"url": {
							"raw": "{{base_url}}/api/materias/?codigo=&activo=&search=&ordering=&page=",
							"host": [
								"{{base_url}}"
							],
							"path": [
								"api",
								"materias",
								""
							],
							"query": [
								{
									"key": "codigo",
									"value": "",
									"description": "Filter by materia codigo (exact match)",
									"disabled": true
								},
								{
									"key": "activo",
									"value": "",
									"description": "Filter by active status (true/false)",
									"disabled": true
								},
								{
									"key": "search",
									"value": "",
									"description": "Search by codigo or nombre",
									"disabled": true
								},
								{
									"key": "ordering",
									"value": "",
									"description": "Order by: codigo, nombre, creditos, fecha_creacion",
									"disabled": true
								},
								{
									"key": "page",
									"value": "",
									"description": "Page number for pagination",
									"disabled": true
								}
							]
						},
						"description": "List all materias (subjects/courses).\n\n**Query Parameters:**\n- `codigo`: Filter by exact materia codigo\n- `activo`: Filter by active status (true/false)\n- `search`: Search by codigo or nombre\n- `ordering`: Order results by 'codigo', 'nombre', 'creditos', or 'fecha_creacion' (prefix with '-' for descending)\n- `page`: Page number for pagination\n\n**Examples:**\n- `GET /api/materias/?activo=true` - Get only active materias\n- `GET /api/materias/?search=PROGRAMACION&ordering=nombre` - Search and order by nombre"
					},
					"response": [
						{
							"name": "Success Response",
							"originalRequest": {
								"method": "GET",
								"header": [],
								"url": {
									"raw": "{{base_url}}/api/materias/",
									"host": [
										"{{base_url}}"
									],
									"path": [
										"api",
										"materias",
										""
									]
								}
							},
							"status": "OK",
							"code": 200,
							"_postman_previewlanguage": "json",
							"header": [
								{
									"key": "Content-Type",
									"value": "application/json"
								}
							],
							"body": "{\n    \"count\": 100,\n    \"next\": \"{{base_url}}/api/materias/?page=2\",\n    \"previous\": null,\n    \"results\": [\n        {\n            \"id\": \"123e4567-e89b-12d3-a456-426614174000\",\n            \"codigo\": \"CIM40\",\n            \"nombre\": \"ELECTROMAGNETÍSMO CIM\",\n            \"creditos\": 10,\n            \"activo\": true,\n            \"fecha_creacion\": \"2024-01-01T00:00:00Z\",\n            \"fecha_modificacion\": \"2024-01-01T00:00:00Z\"\n        }\n    ]\n}"
						}
					]
				},
				{
					"name": "Get Materia by ID",
					"request": {
						"method": "GET",
						"header": [],
						"url": {
							"raw": "{{base_url}}/api/materias/:id/",
							"host": [
								"{{base_url}}"
							],
							"path": [
								"api",
								"materias",
								":id",
								""
							],
							"variable": [
								{
									"key": "id",
									"value": "123e4567-e89b-12d3-a456-426614174000",
									"description": "UUID of the materia"
								}
							]
						},
						"description": "Retrieve a specific materia with detailed information including unidades and planes count.\n\n**Path Parameters:**\n- `id`: UUID of the materia\n\n**Response includes:**\n- Basic materia information\n- List of unidades aprobables\n- Count of plans that include this materia\n\n**Example:**\n- `GET /api/materias/123e4567-e89b-12d3-a456-426614174000/`"
					},
					"response": [
						{
							"name": "Success Response",
							"originalRequest": {
								"method": "GET",
								"header": [],
								"url": {
									"raw": "{{base_url}}/api/materias/123e4567-e89b-12d3-a456-426614174000/",
									"host": [
										"{{base_url}}"
									],
									"path": [
										"api",
										"materias",
										"123e4567-e89b-12d3-a456-426614174000",
										""
									]
								}
							},
							"status": "OK",
							"code": 200,
							"_postman_previewlanguage": "json",
							"header": [
								{
									"key": "Content-Type",
									"value": "application/json"
								}
							],
							"body": "{\n    \"id\": \"123e4567-e89b-12d3-a456-426614174000\",\n    \"codigo\": \"CIM40\",\n    \"nombre\": \"ELECTROMAGNETÍSMO CIM\",\n    \"creditos\": 10,\n    \"activo\": true,\n    \"unidades\": [\n        {\n            \"id\": \"223e4567-e89b-12d3-a456-426614174001\",\n            \"tipo\": \"CURSO\",\n            \"tipo_display\": \"Curso\",\n            \"codigo_bedelias\": \"1267\",\n            \"nombre\": \"\",\n            \"activo\": true\n        }\n    ],\n    \"planes_count\": 3,\n    \"fecha_creacion\": \"2024-01-01T00:00:00Z\",\n    \"fecha_modificacion\": \"2024-01-01T00:00:00Z\"\n}"
						}
					]
				}
			],
			"description": "Endpoints for managing materias (subjects/courses)"
		},
		{
			"name": "Planes de Estudio",
			"item": [
				{
					"name": "List Planes de Estudio",
					"request": {
						"method": "GET",
						"header": [],
						"url": {
							"raw": "{{base_url}}/api/planes-estudio/?carrera=&anio=&activo=&search=&ordering=&page=",
							"host": [
								"{{base_url}}"
							],
							"path": [
								"api",
								"planes-estudio",
								""
							],
							"query": [
								{
									"key": "carrera",
									"value": "",
									"description": "Filter by carrera UUID",
									"disabled": true
								},
								{
									"key": "anio",
									"value": "",
									"description": "Filter by plan year",
									"disabled": true
								},
								{
									"key": "activo",
									"value": "",
									"description": "Filter by active status (true/false)",
									"disabled": true
								},
								{
									"key": "search",
									"value": "",
									"description": "Search by carrera nombre, anio, or descripcion",
									"disabled": true
								},
								{
									"key": "ordering",
									"value": "",
									"description": "Order by: anio, fecha_creacion",
									"disabled": true
								},
								{
									"key": "page",
									"value": "",
									"description": "Page number for pagination",
									"disabled": true
								}
							]
						},
						"description": "List all planes de estudio (study plans).\n\n**Query Parameters:**\n- `carrera`: Filter by carrera UUID\n- `anio`: Filter by plan year\n- `activo`: Filter by active status (true/false)\n- `search`: Search by carrera nombre, anio, or descripcion\n- `ordering`: Order results by 'anio' or 'fecha_creacion' (prefix with '-' for descending)\n- `page`: Page number for pagination\n\n**Examples:**\n- `GET /api/planes-estudio/?carrera=<uuid>&activo=true` - Get active plans for a carrera\n- `GET /api/planes-estudio/?anio=2021` - Get plans for a specific year"
					},
					"response": [
						{
							"name": "Success Response",
							"originalRequest": {
								"method": "GET",
								"header": [],
								"url": {
									"raw": "{{base_url}}/api/planes-estudio/",
									"host": [
										"{{base_url}}"
									],
									"path": [
										"api",
										"planes-estudio",
										""
									]
								}
							},
							"status": "OK",
							"code": 200,
							"_postman_previewlanguage": "json",
							"header": [
								{
									"key": "Content-Type",
									"value": "application/json"
								}
							],
							"body": "{\n    \"count\": 25,\n    \"next\": \"{{base_url}}/api/planes-estudio/?page=2\",\n    \"previous\": null,\n    \"results\": [\n        {\n            \"id\": \"123e4567-e89b-12d3-a456-426614174000\",\n            \"carrera\": {\n                \"id\": \"223e4567-e89b-12d3-a456-426614174001\",\n                \"nombre\": \"INGENIERÍA CIVIL\",\n                \"fecha_creacion\": \"2024-01-01T00:00:00Z\",\n                \"fecha_modificacion\": \"2024-01-01T00:00:00Z\"\n            },\n            \"carrera_id\": \"223e4567-e89b-12d3-a456-426614174001\",\n            \"carrera_nombre\": \"INGENIERÍA CIVIL\",\n            \"anio\": \"2021\",\n            \"descripcion\": \"\",\n            \"activo\": true,\n            \"materias_count\": 45,\n            \"fecha_creacion\": \"2024-01-01T00:00:00Z\",\n            \"fecha_modificacion\": \"2024-01-01T00:00:00Z\"\n        }\n    ]\n}"
						}
					]
				},
				{
					"name": "Get Plan de Estudio by ID",
					"request": {
						"method": "GET",
						"header": [],
						"url": {
							"raw": "{{base_url}}/api/planes-estudio/:id/",
							"host": [
								"{{base_url}}"
							],
							"path": [
								"api",
								"planes-estudio",
								":id",
								""
							],
							"variable": [
								{
									"key": "id",
									"value": "123e4567-e89b-12d3-a456-426614174000",
									"description": "UUID of the plan de estudio"
								}
							]
						},
						"description": "Retrieve a specific plan de estudio by its UUID.\n\n**Path Parameters:**\n- `id`: UUID of the plan de estudio\n\n**Example:**\n- `GET /api/planes-estudio/123e4567-e89b-12d3-a456-426614174000/`"
					},
					"response": [
						{
							"name": "Success Response",
							"originalRequest": {
								"method": "GET",
								"header": [],
								"url": {
									"raw": "{{base_url}}/api/planes-estudio/123e4567-e89b-12d3-a456-426614174000/",
									"host": [
										"{{base_url}}"
									],
									"path": [
										"api",
										"planes-estudio",
										"123e4567-e89b-12d3-a456-426614174000",
										""
									]
								}
							},
							"status": "OK",
							"code": 200,
							"_postman_previewlanguage": "json",
							"header": [
								{
									"key": "Content-Type",
									"value": "application/json"
								}
							],
							"body": "{\n    \"id\": \"123e4567-e89b-12d3-a456-426614174000\",\n    \"carrera\": {\n        \"id\": \"223e4567-e89b-12d3-a456-426614174001\",\n        \"nombre\": \"INGENIERÍA CIVIL\",\n        \"fecha_creacion\": \"2024-01-01T00:00:00Z\",\n        \"fecha_modificacion\": \"2024-01-01T00:00:00Z\"\n    },\n    \"carrera_id\": \"223e4567-e89b-12d3-a456-426614174001\",\n    \"carrera_nombre\": \"INGENIERÍA CIVIL\",\n    \"anio\": \"2021\",\n    \"descripcion\": \"\",\n    \"activo\": true,\n    \"materias_count\": 45,\n    \"fecha_creacion\": \"2024-01-01T00:00:00Z\",\n    \"fecha_modificacion\": \"2024-01-01T00:00:00Z\"\n}"
						}
					]
				}
			],
			"description": "Endpoints for managing planes de estudio (study plans)"
		},
		{
			"name": "Planes-Materias",
			"item": [
				{
					"name": "List Planes-Materias",
					"request": {
						"method": "GET",
						"header": [],
						"url": {
							"raw": "{{base_url}}/api/planes-materias/?plan=&materia=&obligatorio=&search=&ordering=&page=",
							"host": [
								"{{base_url}}"
							],
							"path": [
								"api",
								"planes-materias",
								""
							],
							"query": [
								{
									"key": "plan",
									"value": "",
									"description": "Filter by plan UUID",
									"disabled": true
								},
								{
									"key": "materia",
									"value": "",
									"description": "Filter by materia UUID",
									"disabled": true
								},
								{
									"key": "obligatorio",
									"value": "",
									"description": "Filter by obligatorio status (true/false)",
									"disabled": true
								},
								{
									"key": "search",
									"value": "",
									"description": "Search by carrera nombre, plan anio, materia codigo, or materia nombre",
									"disabled": true
								},
								{
									"key": "ordering",
									"value": "",
									"description": "Order by: semestre_sugerido, fecha_creacion",
									"disabled": true
								},
								{
									"key": "page",
									"value": "",
									"description": "Page number for pagination",
									"disabled": true
								}
							]
						},
						"description": "List all plan-materia relationships.\n\n**Query Parameters:**\n- `plan`: Filter by plan UUID\n- `materia`: Filter by materia UUID\n- `obligatorio`: Filter by obligatorio status (true/false)\n- `search`: Search by carrera nombre, plan anio, materia codigo, or materia nombre\n- `ordering`: Order results by 'semestre_sugerido' or 'fecha_creacion' (prefix with '-' for descending)\n- `page`: Page number for pagination\n\n**Examples:**\n- `GET /api/planes-materias/?plan=<uuid>` - Get all materias in a specific plan\n- `GET /api/planes-materias/?materia=<uuid>` - Get all plans that include a specific materia"
					},
					"response": [
						{
							"name": "Success Response",
							"originalRequest": {
								"method": "GET",
								"header": [],
								"url": {
									"raw": "{{base_url}}/api/planes-materias/",
									"host": [
										"{{base_url}}"
									],
									"path": [
										"api",
										"planes-materias",
										""
									]
								}
							},
							"status": "OK",
							"code": 200,
							"_postman_previewlanguage": "json",
							"header": [
								{
									"key": "Content-Type",
									"value": "application/json"
								}
							],
							"body": "{\n    \"count\": 500,\n    \"next\": \"{{base_url}}/api/planes-materias/?page=2\",\n    \"previous\": null,\n    \"results\": [\n        {\n            \"id\": \"123e4567-e89b-12d3-a456-426614174000\",\n            \"plan\": {\n                \"id\": \"223e4567-e89b-12d3-a456-426614174001\",\n                \"carrera\": {\n                    \"id\": \"323e4567-e89b-12d3-a456-426614174002\",\n                    \"nombre\": \"INGENIERÍA CIVIL\",\n                    \"fecha_creacion\": \"2024-01-01T00:00:00Z\",\n                    \"fecha_modificacion\": \"2024-01-01T00:00:00Z\"\n                },\n                \"carrera_id\": \"323e4567-e89b-12d3-a456-426614174002\",\n                \"carrera_nombre\": \"INGENIERÍA CIVIL\",\n                \"anio\": \"2021\",\n                \"descripcion\": \"\",\n                \"activo\": true,\n                \"materias_count\": 45,\n                \"fecha_creacion\": \"2024-01-01T00:00:00Z\",\n                \"fecha_modificacion\": \"2024-01-01T00:00:00Z\"\n            },\n            \"plan_id\": \"223e4567-e89b-12d3-a456-426614174001\",\n            \"materia\": {\n                \"id\": \"423e4567-e89b-12d3-a456-426614174003\",\n                \"codigo\": \"CIM40\",\n                \"nombre\": \"ELECTROMAGNETÍSMO CIM\",\n                \"creditos\": 10,\n                \"activo\": true,\n                \"fecha_creacion\": \"2024-01-01T00:00:00Z\",\n                \"fecha_modificacion\": \"2024-01-01T00:00:00Z\"\n            },\n            \"materia_id\": \"423e4567-e89b-12d3-a456-426614174003\",\n            \"materia_codigo\": \"CIM40\",\n            \"materia_nombre\": \"ELECTROMAGNETÍSMO CIM\",\n            \"obligatorio\": true,\n            \"semestre_sugerido\": 3,\n            \"fecha_creacion\": \"2024-01-01T00:00:00Z\",\n            \"fecha_modificacion\": \"2024-01-01T00:00:00Z\"\n        }\n    ]\n}"
						}
					]
				},
				{
					"name": "Get Plan-Materia by ID",
					"request": {
						"method": "GET",
						"header": [],
						"url": {
							"raw": "{{base_url}}/api/planes-materias/:id/",
							"host": [
								"{{base_url}}"
							],
							"path": [
								"api",
								"planes-materias",
								":id",
								""
							],
							"variable": [
								{
									"key": "id",
									"value": "123e4567-e89b-12d3-a456-426614174000",
									"description": "UUID of the plan-materia relationship"
								}
							]
						},
						"description": "Retrieve a specific plan-materia relationship by its UUID.\n\n**Path Parameters:**\n- `id`: UUID of the plan-materia relationship\n\n**Example:**\n- `GET /api/planes-materias/123e4567-e89b-12d3-a456-426614174000/`"
					},
					"response": []
				}
			],
			"description": "Endpoints for managing plan-materia relationships"
		},
		{
			"name": "Unidades Aprobables",
			"item": [
				{
					"name": "List Unidades Aprobables",
					"request": {
						"method": "GET",
						"header": [],
						"url": {
							"raw": "{{base_url}}/api/unidades-aprobables/?materia=&tipo=&activo=&search=&ordering=&page=",
							"host": [
								"{{base_url}}"
							],
							"path": [
								"api",
								"unidades-aprobables",
								""
							],
							"query": [
								{
									"key": "materia",
									"value": "",
									"description": "Filter by materia UUID",
									"disabled": true
								},
								{
									"key": "tipo",
									"value": "",
									"description": "Filter by tipo: CURSO, EXAMEN, UCB, OTRO",
									"disabled": true
								},
								{
									"key": "activo",
									"value": "",
									"description": "Filter by active status (true/false)",
									"disabled": true
								},
								{
									"key": "search",
									"value": "",
									"description": "Search by materia codigo, materia nombre, codigo_bedelias, or nombre",
									"disabled": true
								},
								{
									"key": "ordering",
									"value": "",
									"description": "Order by: materia__codigo, tipo, fecha_creacion",
									"disabled": true
								},
								{
									"key": "page",
									"value": "",
									"description": "Page number for pagination",
									"disabled": true
								}
							]
						},
						"description": "List all unidades aprobables (approvable units: courses, exams, UCB modules, etc.).\n\n**Query Parameters:**\n- `materia`: Filter by materia UUID\n- `tipo`: Filter by tipo (CURSO, EXAMEN, UCB, OTRO)\n- `activo`: Filter by active status (true/false)\n- `search`: Search by materia codigo, materia nombre, codigo_bedelias, or nombre\n- `ordering`: Order results by 'materia__codigo', 'tipo', or 'fecha_creacion' (prefix with '-' for descending)\n- `page`: Page number for pagination\n\n**Examples:**\n- `GET /api/unidades-aprobables/?materia=<uuid>&tipo=CURSO` - Get curso unidades for a materia\n- `GET /api/unidades-aprobables/?activo=true` - Get only active unidades"
					},
					"response": [
						{
							"name": "Success Response",
							"originalRequest": {
								"method": "GET",
								"header": [],
								"url": {
									"raw": "{{base_url}}/api/unidades-aprobables/",
									"host": [
										"{{base_url}}"
									],
									"path": [
										"api",
										"unidades-aprobables",
										""
									]
								}
							},
							"status": "OK",
							"code": 200,
							"_postman_previewlanguage": "json",
							"header": [
								{
									"key": "Content-Type",
									"value": "application/json"
								}
							],
							"body": "{\n    \"count\": 200,\n    \"next\": \"{{base_url}}/api/unidades-aprobables/?page=2\",\n    \"previous\": null,\n    \"results\": [\n        {\n            \"id\": \"123e4567-e89b-12d3-a456-426614174000\",\n            \"materia\": {\n                \"id\": \"223e4567-e89b-12d3-a456-426614174001\",\n                \"codigo\": \"CIM40\",\n                \"nombre\": \"ELECTROMAGNETÍSMO CIM\",\n                \"creditos\": 10,\n                \"activo\": true,\n                \"fecha_creacion\": \"2024-01-01T00:00:00Z\",\n                \"fecha_modificacion\": \"2024-01-01T00:00:00Z\"\n            },\n            \"materia_id\": \"223e4567-e89b-12d3-a456-426614174001\",\n            \"materia_codigo\": \"CIM40\",\n            \"materia_nombre\": \"ELECTROMAGNETÍSMO CIM\",\n            \"tipo\": \"CURSO\",\n            \"tipo_display\": \"Curso\",\n            \"codigo_bedelias\": \"1267\",\n            \"nombre\": \"\",\n            \"activo\": true,\n            \"fecha_creacion\": \"2024-01-01T00:00:00Z\",\n            \"fecha_modificacion\": \"2024-01-01T00:00:00Z\"\n        }\n    ]\n}"
						}
					]
				},
				{
					"name": "Get Unidad Aprobable by ID",
					"request": {
						"method": "GET",
						"header": [],
						"url": {
							"raw": "{{base_url}}/api/unidades-aprobables/:id/",
							"host": [
								"{{base_url}}"
							],
							"path": [
								"api",
								"unidades-aprobables",
								":id",
								""
							],
							"variable": [
								{
									"key": "id",
									"value": "123e4567-e89b-12d3-a456-426614174000",
									"description": "UUID of the unidad aprobable"
								}
							]
						},
						"description": "Retrieve a specific unidad aprobable by its UUID.\n\n**Path Parameters:**\n- `id`: UUID of the unidad aprobable\n\n**Example:**\n- `GET /api/unidades-aprobables/123e4567-e89b-12d3-a456-426614174000/`"
					},
					"response": []
				}
			],
			"description": "Endpoints for managing unidades aprobables (approvable units)"
		},
		{
			"name": "Requisitos Nodos",
			"item": [
				{
					"name": "List Requisitos Nodos",
					"request": {
						"method": "GET",
						"header": [],
						"url": {
							"raw": "{{base_url}}/api/requisitos-nodos/?plan_materia=&tipo=&padre=&root_only=&search=&ordering=&page=",
							"host": [
								"{{base_url}}"
							],
							"path": [
								"api",
								"requisitos-nodos",
								""
							],
							"query": [
								{
									"key": "plan_materia",
									"value": "",
									"description": "Filter by plan_materia UUID",
									"disabled": true
								},
								{
									"key": "tipo",
									"value": "",
									"description": "Filter by tipo: ALL, ANY, NOT, LEAF",
									"disabled": true
								},
								{
									"key": "padre",
									"value": "",
									"description": "Filter by padre UUID",
									"disabled": true
								},
								{
									"key": "root_only",
									"value": "",
									"description": "Filter to show only root nodes (true/false)",
									"disabled": true
								},
								{
									"key": "search",
									"value": "",
									"description": "Search by descripcion",
									"disabled": true
								},
								{
									"key": "ordering",
									"value": "",
									"description": "Order by: orden, fecha_creacion",
									"disabled": true
								},
								{
									"key": "page",
									"value": "",
									"description": "Page number for pagination",
									"disabled": true
								}
							]
						},
						"description": "List all requisitos nodos (requirement nodes).\n\n**Query Parameters:**\n- `plan_materia`: Filter by plan_materia UUID\n- `tipo`: Filter by tipo (ALL, ANY, NOT, LEAF)\n- `padre`: Filter by padre UUID\n- `root_only`: Filter to show only root nodes (true/false)\n- `search`: Search by descripcion\n- `ordering`: Order results by 'orden' or 'fecha_creacion' (prefix with '-' for descending)\n- `page`: Page number for pagination\n\n**Examples:**\n- `GET /api/requisitos-nodos/?plan_materia=<uuid>` - Get all requisitos for a plan-materia\n- `GET /api/requisitos-nodos/?root_only=true` - Get only root nodes\n- `GET /api/requisitos-nodos/?tipo=LEAF` - Get only leaf nodes"
					},
					"response": [
						{
							"name": "Success Response",
							"originalRequest": {
								"method": "GET",
								"header": [],
								"url": {
									"raw": "{{base_url}}/api/requisitos-nodos/",
									"host": [
										"{{base_url}}"
									],
									"path": [
										"api",
										"requisitos-nodos",
										""
									]
								}
							},
							"status": "OK",
							"code": 200,
							"_postman_previewlanguage": "json",
							"header": [
								{
									"key": "Content-Type",
									"value": "application/json"
								}
							],
							"body": "{\n    \"count\": 150,\n    \"next\": \"{{base_url}}/api/requisitos-nodos/?page=2\",\n    \"previous\": null,\n    \"results\": [\n        {\n            \"id\": \"123e4567-e89b-12d3-a456-426614174000\",\n            \"plan_materia_id\": \"223e4567-e89b-12d3-a456-426614174001\",\n            \"tipo\": \"ALL\",\n            \"tipo_display\": \"Debe cumplir todas\",\n            \"padre_id\": null,\n            \"cantidad_minima\": null,\n            \"orden\": 0,\n            \"descripcion\": \"\",\n            \"hijos_count\": 2,\n            \"items_count\": 0,\n            \"fecha_creacion\": \"2024-01-01T00:00:00Z\",\n            \"fecha_modificacion\": \"2024-01-01T00:00:00Z\"\n        }\n    ]\n}"
						}
					]
				},
				{
					"name": "Get Requisito Nodo by ID",
					"request": {
						"method": "GET",
						"header": [],
						"url": {
							"raw": "{{base_url}}/api/requisitos-nodos/:id/?tree=",
							"host": [
								"{{base_url}}"
							],
							"path": [
								"api",
								"requisitos-nodos",
								":id",
								""
							],
							"query": [
								{
									"key": "tree",
									"value": "",
									"description": "Return full tree structure (true/false)",
									"disabled": true
								}
							],
							"variable": [
								{
									"key": "id",
									"value": "123e4567-e89b-12d3-a456-426614174000",
									"description": "UUID of the requisito nodo"
								}
							]
						},
						"description": "Retrieve a specific requisito nodo by its UUID.\n\n**Path Parameters:**\n- `id`: UUID of the requisito nodo\n\n**Query Parameters:**\n- `tree`: Set to 'true' to return the full recursive tree structure with hijos and items\n\n**Examples:**\n- `GET /api/requisitos-nodos/123e4567-e89b-12d3-a456-426614174000/` - Get basic nodo info\n- `GET /api/requisitos-nodos/123e4567-e89b-12d3-a456-426614174000/?tree=true` - Get full tree structure"
					},
					"response": [
						{
							"name": "Basic Response",
							"originalRequest": {
								"method": "GET",
								"header": [],
								"url": {
									"raw": "{{base_url}}/api/requisitos-nodos/123e4567-e89b-12d3-a456-426614174000/",
									"host": [
										"{{base_url}}"
									],
									"path": [
										"api",
										"requisitos-nodos",
										"123e4567-e89b-12d3-a456-426614174000",
										""
									]
								}
							},
							"status": "OK",
							"code": 200,
							"_postman_previewlanguage": "json",
							"header": [
								{
									"key": "Content-Type",
									"value": "application/json"
								}
							],
							"body": "{\n    \"id\": \"123e4567-e89b-12d3-a456-426614174000\",\n    \"plan_materia_id\": \"223e4567-e89b-12d3-a456-426614174001\",\n    \"tipo\": \"ALL\",\n    \"tipo_display\": \"Debe cumplir todas\",\n    \"padre_id\": null,\n    \"cantidad_minima\": null,\n    \"orden\": 0,\n    \"descripcion\": \"\",\n    \"hijos_count\": 2,\n    \"items_count\": 0,\n    \"fecha_creacion\": \"2024-01-01T00:00:00Z\",\n    \"fecha_modificacion\": \"2024-01-01T00:00:00Z\"\n}"
						},
						{
							"name": "Tree Response",
							"originalRequest": {
								"method": "GET",
								"header": [],
								"url": {
									"raw": "{{base_url}}/api/requisitos-nodos/123e4567-e89b-12d3-a456-426614174000/?tree=true",
									"host": [
										"{{base_url}}"
									],
									"path": [
										"api",
										"requisitos-nodos",
										"123e4567-e89b-12d3-a456-426614174000",
										""
									],
									"query": [
										{
											"key": "tree",
											"value": "true"
										}
									]
								}
							},
							"status": "OK",
							"code": 200,
							"_postman_previewlanguage": "json",
							"header": [
								{
									"key": "Content-Type",
									"value": "application/json"
								}
							],
							"body": "{\n    \"id\": \"123e4567-e89b-12d3-a456-426614174000\",\n    \"plan_materia_id\": \"223e4567-e89b-12d3-a456-426614174001\",\n    \"tipo\": \"ALL\",\n    \"tipo_display\": \"Debe cumplir todas\",\n    \"cantidad_minima\": null,\n    \"orden\": 0,\n    \"descripcion\": \"\",\n    \"hijos\": [\n        {\n            \"id\": \"323e4567-e89b-12d3-a456-426614174002\",\n            \"plan_materia_id\": null,\n            \"tipo\": \"LEAF\",\n            \"tipo_display\": \"Condición hoja\",\n            \"cantidad_minima\": null,\n            \"orden\": 0,\n            \"descripcion\": \"\",\n            \"hijos\": [],\n            \"items\": [\n                {\n                    \"id\": \"423e4567-e89b-12d3-a456-426614174003\",\n                    \"nodo_id\": \"323e4567-e89b-12d3-a456-426614174002\",\n                    \"tipo\": \"UNIDAD\",\n                    \"tipo_display\": \"Unidad aprobable específica\",\n                    \"unidad_requerida\": {\n                        \"id\": \"523e4567-e89b-12d3-a456-426614174004\",\n                        \"materia\": {\n                            \"id\": \"623e4567-e89b-12d3-a456-426614174005\",\n                            \"codigo\": \"CIM40\",\n                            \"nombre\": \"ELECTROMAGNETÍSMO CIM\",\n                            \"creditos\": 10,\n                            \"activo\": true,\n                            \"fecha_creacion\": \"2024-01-01T00:00:00Z\",\n                            \"fecha_modificacion\": \"2024-01-01T00:00:00Z\"\n                        },\n                        \"materia_id\": \"623e4567-e89b-12d3-a456-426614174005\",\n                        \"materia_codigo\": \"CIM40\",\n                        \"materia_nombre\": \"ELECTROMAGNETÍSMO CIM\",\n                        \"tipo\": \"CURSO\",\n                        \"tipo_display\": \"Curso\",\n                        \"codigo_bedelias\": \"1267\",\n                        \"nombre\": \"\",\n                        \"activo\": true,\n                        \"fecha_creacion\": \"2024-01-01T00:00:00Z\",\n                        \"fecha_modificacion\": \"2024-01-01T00:00:00Z\"\n                    },\n                    \"unidad_requerida_id\": \"523e4567-e89b-12d3-a456-426614174004\",\n                    \"creditos_minimos\": null,\n                    \"texto\": \"\",\n                    \"orden\": 0,\n                    \"fecha_creacion\": \"2024-01-01T00:00:00Z\",\n                    \"fecha_modificacion\": \"2024-01-01T00:00:00Z\"\n                }\n            ],\n            \"fecha_creacion\": \"2024-01-01T00:00:00Z\",\n            \"fecha_modificacion\": \"2024-01-01T00:00:00Z\"\n        }\n    ],\n    \"items\": [],\n    \"fecha_creacion\": \"2024-01-01T00:00:00Z\",\n    \"fecha_modificacion\": \"2024-01-01T00:00:00Z\"\n}"
						}
					]
				}
			],
			"description": "Endpoints for managing requisitos nodos (requirement nodes)"
		},
		{
			"name": "Requisitos Items",
			"item": [
				{
					"name": "List Requisitos Items",
					"request": {
						"method": "GET",
						"header": [],
						"url": {
							"raw": "{{base_url}}/api/requisitos-items/?nodo=&tipo=&search=&ordering=&page=",
							"host": [
								"{{base_url}}"
							],
							"path": [
								"api",
								"requisitos-items",
								""
							],
							"query": [
								{
									"key": "nodo",
									"value": "",
									"description": "Filter by nodo UUID",
									"disabled": true
								},
								{
									"key": "tipo",
									"value": "",
									"description": "Filter by tipo: UNIDAD, CREDITOS, TEXTO",
									"disabled": true
								},
								{
									"key": "search",
									"value": "",
									"description": "Search by texto",
									"disabled": true
								},
								{
									"key": "ordering",
									"value": "",
									"description": "Order by: orden, fecha_creacion",
									"disabled": true
								},
								{
									"key": "page",
									"value": "",
									"description": "Page number for pagination",
									"disabled": true
								}
							]
						},
						"description": "List all requisitos items (requirement items).\n\n**Query Parameters:**\n- `nodo`: Filter by nodo UUID\n- `tipo`: Filter by tipo (UNIDAD, CREDITOS, TEXTO)\n- `search`: Search by texto\n- `ordering`: Order results by 'orden' or 'fecha_creacion' (prefix with '-' for descending)\n- `page`: Page number for pagination\n\n**Examples:**\n- `GET /api/requisitos-items/?nodo=<uuid>` - Get all items for a specific nodo\n- `GET /api/requisitos-items/?tipo=UNIDAD` - Get only UNIDAD type items"
					},
					"response": [
						{
							"name": "Success Response",
							"originalRequest": {
								"method": "GET",
								"header": [],
								"url": {
									"raw": "{{base_url}}/api/requisitos-items/",
									"host": [
										"{{base_url}}"
									],
									"path": [
										"api",
										"requisitos-items",
										""
									]
								}
							},
							"status": "OK",
							"code": 200,
							"_postman_previewlanguage": "json",
							"header": [
								{
									"key": "Content-Type",
									"value": "application/json"
								}
							],
							"body": "{\n    \"count\": 300,\n    \"next\": \"{{base_url}}/api/requisitos-items/?page=2\",\n    \"previous\": null,\n    \"results\": [\n        {\n            \"id\": \"123e4567-e89b-12d3-a456-426614174000\",\n            \"nodo_id\": \"223e4567-e89b-12d3-a456-426614174001\",\n            \"tipo\": \"UNIDAD\",\n            \"tipo_display\": \"Unidad aprobable específica\",\n            \"unidad_requerida\": {\n                \"id\": \"323e4567-e89b-12d3-a456-426614174002\",\n                \"materia\": {\n                    \"id\": \"423e4567-e89b-12d3-a456-426614174003\",\n                    \"codigo\": \"CIM40\",\n                    \"nombre\": \"ELECTROMAGNETÍSMO CIM\",\n                    \"creditos\": 10,\n                    \"activo\": true,\n                    \"fecha_creacion\": \"2024-01-01T00:00:00Z\",\n                    \"fecha_modificacion\": \"2024-01-01T00:00:00Z\"\n                },\n                \"materia_id\": \"423e4567-e89b-12d3-a456-426614174003\",\n                \"materia_codigo\": \"CIM40\",\n                \"materia_nombre\": \"ELECTROMAGNETÍSMO CIM\",\n                \"tipo\": \"CURSO\",\n                \"tipo_display\": \"Curso\",\n                \"codigo_bedelias\": \"1267\",\n                \"nombre\": \"\",\n                \"activo\": true,\n                \"fecha_creacion\": \"2024-01-01T00:00:00Z\",\n                \"fecha_modificacion\": \"2024-01-01T00:00:00Z\"\n            },\n            \"unidad_requerida_id\": \"323e4567-e89b-12d3-a456-426614174002\",\n            \"creditos_minimos\": null,\n            \"texto\": \"\",\n            \"orden\": 0,\n            \"fecha_creacion\": \"2024-01-01T00:00:00Z\",\n            \"fecha_modificacion\": \"2024-01-01T00:00:00Z\"\n        }\n    ]\n}"
						}
					]
				},
				{
					"name": "Get Requisito Item by ID",
					"request": {
						"method": "GET",
						"header": [],
						"url": {
							"raw": "{{base_url}}/api/requisitos-items/:id/",
							"host": [
								"{{base_url}}"
							],
							"path": [
								"api",
								"requisitos-items",
								":id",
								""
							],
							"variable": [
								{
									"key": "id",
									"value": "123e4567-e89b-12d3-a456-426614174000",
									"description": "UUID of the requisito item"
								}
							]
						},
						"description": "Retrieve a specific requisito item by its UUID.\n\n**Path Parameters:**\n- `id`: UUID of the requisito item\n\n**Example:**\n- `GET /api/requisitos-items/123e4567-e89b-12d3-a456-426614174000/`"
					},
					"response": []
				}
			],
			"description": "Endpoints for managing requisitos items (requirement items)"
		}
	],
	"variable": [
		{
			"key": "base_url",
			"value": "http://localhost:8000",
			"type": "string"
		}
	]
}

